{"stats":{"minecraft:custom":{"minecraft:jump":24,"minecraft:time_since_rest":3967,"minecraft:damage_dealt":10,"minecraft:damage_taken":20,"minecraft:sprint_one_cm":3392,"minecraft:play_time":3967,"minecraft:time_since_death":3967,"minecraft:walk_one_cm":15896,"minecraft:climb_one_cm":405,"minecraft:total_world_time":3967,"minecraft:fall_one_cm":685,"minecraft:fly_one_cm":1972},"minecraft:mined":{"minecraft:jungle_leaves":1,"minecraft:vine":1,"minecraft:jungle_log":3,"minecraft:oak_leaves":1},"minecraft:crafted":{"minecraft:jungle_planks":12},"minecraft:picked_up":{"minecraft:jungle_log":3}},"DataVersion":3953}